cucumber_tag_expressions/__init__.py
cucumber_tag_expressions/model.py
cucumber_tag_expressions/parser.py
cucumber_tag_expressions-9.0.0.dist-info/licenses/LICENSE
cucumber_tag_expressions-9.0.0.dist-info/WHEEL
cucumber_tag_expressions-9.0.0.dist-info/METADATA
cucumber_tag_expressions-9.0.0.dist-info/RECORD
