Metadata-Version: 2.4
Name: cucumber-tag-expressions
Version: 9.0.0
Summary: Provides a tag-expression parser and evaluation logic for cucumber/behave
Keywords: BDD,testing,cucumber,tag-expressions,behave
Author: Jens Engel
Author-email: Jens Engel <jenisys@noreply.github.com>
License-Expression: MIT
License-File: LICENSE
Classifier: Development Status :: 5 - Production/Stable
Classifier: Environment :: Console
Classifier: Intended Audience :: Developers
Classifier: Operating System :: OS Independent
Classifier: Programming Language :: Python :: 3.10
Classifier: Programming Language :: Python :: 3.11
Classifier: Programming Language :: Python :: 3.12
Classifier: Programming Language :: Python :: 3.13
Classifier: Programming Language :: Python :: 3.14
Classifier: Programming Language :: Python :: Implementation :: CPython
Classifier: Programming Language :: Python :: Implementation :: PyPy
Classifier: Topic :: Software Development :: Testing
Classifier: Topic :: Software Development :: Libraries :: Python Modules
Requires-Python: >=3.10
Project-URL: Homepage, https://github.com/cucumber/tag-expressions
Project-URL: Download, https://pypi.org/project/cucumber-tag-expressions
Project-URL: Repository, https://github.com/cucumber/tag-expressions
Project-URL: Issues, https://github.com/cucumber/tag-expressions/issues/
Project-URL: Changelog, https://github.com/cucumber/tag-expressions/releases
